PyMCTranslate/__init__.py
PyMCTranslate/_version.py
PyMCTranslate/build_number.json
PyMCTranslate/__pyinstaller/__init__.py
PyMCTranslate/__pyinstaller/hook-PyMCTranslate.py
PyMCTranslate/code_functions/__init__.py
PyMCTranslate/code_functions/banner_pattern_2u.py
PyMCTranslate/code_functions/banner_pattern_fu.py
PyMCTranslate/code_functions/bedrock_chest_connection_other_left.py
PyMCTranslate/code_functions/bedrock_chest_connection_other_left_120.py
PyMCTranslate/code_functions/bedrock_chest_connection_other_right.py
PyMCTranslate/code_functions/bedrock_chest_connection_other_right_120.py
PyMCTranslate/code_functions/bedrock_chest_connection_self.py
PyMCTranslate/code_functions/bedrock_chest_connection_self_120.py
PyMCTranslate/code_functions/bedrock_chest_fu.py
PyMCTranslate/code_functions/bedrock_cmd_custom_name_2u.py
PyMCTranslate/code_functions/bedrock_cmd_custom_name_fu.py
PyMCTranslate/code_functions/bedrock_moving_block_pos_2u.py
PyMCTranslate/code_functions/bedrock_moving_block_pos_fu.py
PyMCTranslate/code_functions/bedrock_sign_2u.py
PyMCTranslate/code_functions/bedrock_sign_2u_120.py
PyMCTranslate/code_functions/bedrock_sign_fu.py
PyMCTranslate/code_functions/bedrock_sign_fu_120.py
PyMCTranslate/code_functions/bedrock_skull_rotation_2u.py
PyMCTranslate/code_functions/java_sign_2u_120.py
PyMCTranslate/code_functions/java_sign_2u_1215.py
PyMCTranslate/code_functions/java_sign_2u_19.py
PyMCTranslate/code_functions/java_sign_fu_120.py
PyMCTranslate/code_functions/java_sign_fu_1215.py
PyMCTranslate/code_functions/java_sign_fu_19.py
PyMCTranslate/code_functions/java_skull_fu_116.py
PyMCTranslate/code_functions/java_skull_fu_1215.py
PyMCTranslate/code_functions/java_skull_fu_19.py
PyMCTranslate/min_json/atlas.json.gz
PyMCTranslate/min_json/versions/bedrock_1_10_0/block.json.gz
PyMCTranslate/min_json/versions/bedrock_1_10_0/meta.json.gz
PyMCTranslate/min_json/versions/bedrock_1_11_0/block.json.gz
PyMCTranslate/min_json/versions/bedrock_1_11_0/meta.json.gz
pymctranslate-1.2.40.dist-info/licenses/LICENSE
pymctranslate-1.2.40.dist-info/METADATA
pymctranslate-1.2.40.dist-info/WHEEL
pymctranslate-1.2.40.dist-info/entry_points.txt
pymctranslate-1.2.40.dist-info/top_level.txt
pymctranslate-1.2.40.dist-info/RECORD
