Metadata-Version: 2.4
Name: PyMCTranslate
Version: 1.2.40
Summary: A Minecraft data translation system.
Home-page: https://www.amuletmc.com
Author: James Clare
Author-email: amuleteditor@gmail.com
Platform: any
Classifier: Programming Language :: Python :: 3
Classifier: Operating System :: OS Independent
Requires-Python: ~=3.10
License-File: LICENSE
Requires-Dist: numpy~=1.17
Requires-Dist: amulet-nbt~=2.0
Provides-Extra: docs
Requires-Dist: Sphinx>=1.7.4; extra == "docs"
Requires-Dist: sphinx-autodoc-typehints>=1.3.0; extra == "docs"
Requires-Dist: sphinx_rtd_theme>=0.3.1; extra == "docs"
Provides-Extra: dev
Requires-Dist: black>=22.3; extra == "dev"
Requires-Dist: pre_commit>=1.11.1; extra == "dev"
Dynamic: license-file
